snaptrade_client/__init__.py
snaptrade_client/api_client.py
snaptrade_client/api_response.py
snaptrade_client/apis/__init__.py
snaptrade_client/apis/path_to_api.py
snaptrade_client/apis/paths/__init__.py
snaptrade_client/apis/paths/accounts.py
snaptrade_client/apis/paths/accounts_account_id.py
snaptrade_client/apis/paths/accounts_account_id_activities.py
snaptrade_client/apis/paths/accounts_account_id_balances.py
snaptrade_client/apis/paths/accounts_account_id_holdings.py
snaptrade_client/apis/paths/accounts_account_id_options.py
snaptrade_client/apis/paths/accounts_account_id_options_chain.py
snaptrade_client/apis/paths/accounts_account_id_orders.py
snaptrade_client/apis/paths/accounts_account_id_orders_cancel.py
snaptrade_client/apis/paths/accounts_account_id_orders_details.py
snaptrade_client/apis/paths/accounts_account_id_orders_v2.py
snaptrade_client/apis/paths/accounts_account_id_positions.py
snaptrade_client/apis/paths/accounts_account_id_quotes.py
snaptrade_client/apis/paths/accounts_account_id_recent_orders.py
snaptrade_client/apis/paths/accounts_account_id_recent_orders_v2.py
snaptrade_client/apis/paths/accounts_account_id_return_rates.py
snaptrade_client/apis/paths/accounts_account_id_symbols.py
snaptrade_client/apis/paths/accounts_account_id_trading_bracket.py
snaptrade_client/apis/paths/accounts_account_id_trading_cancel.py
snaptrade_client/apis/paths/accounts_account_id_trading_crypto.py
snaptrade_client/apis/paths/accounts_account_id_trading_crypto_preview.py
snaptrade_client/apis/paths/accounts_account_id_trading_instruments_cryptocurrency_pairs.py
snaptrade_client/apis/paths/accounts_account_id_trading_instruments_cryptocurrency_pairs_instrument_symbol_quote.py
snaptrade_client/apis/paths/accounts_account_id_trading_options.py
snaptrade_client/apis/paths/accounts_account_id_trading_replace.py
snaptrade_client/apis/paths/activities.py
snaptrade_client/apis/paths/authorizations.py
snaptrade_client/apis/paths/authorizations_authorization_id.py
snaptrade_python_sdk-11.0.155.dist-info/LICENSE
snaptrade_python_sdk-11.0.155.dist-info/METADATA
snaptrade_python_sdk-11.0.155.dist-info/WHEEL
snaptrade_python_sdk-11.0.155.dist-info/RECORD
