Metadata-Version: 2.1
Name: snaptrade-python-sdk
Version: 11.0.155
Summary: Client for SnapTrade
License: MIT
Author: SnapTrade
Author-email: api@snaptrade.com
Requires-Python: >=3.8,<4.0
Classifier: License :: OSI Approved :: MIT License
Classifier: Programming Language :: Python :: 3
Classifier: Programming Language :: Python :: 3.8
Classifier: Programming Language :: Python :: 3.9
Classifier: Programming Language :: Python :: 3.10
Classifier: Programming Language :: Python :: 3.11
Requires-Dist: aiohttp (>=3.10.11,<4.0.0)
Requires-Dist: certifi (>=2023.7.22)
Requires-Dist: cryptography (>=43.0.3,<44.0.0)
Requires-Dist: frozendict (>=2.3.4,<3.0.0)
Requires-Dist: python-dateutil (>=2.8.2,<3.0.0)
Requires-Dist: typing_extensions (==4.13.2)
Requires-Dist: urllib3 (>=1.26.18,<3.0.0)
